<featureType>
  <id>FeatureTypeInfoImpl-278efbc3:17f5052b3fc:-7feb</id>
  <name>ne_10m_populated_places</name>
  <nativeName>ne_10m_populated_places</nativeName>
  <namespace>
    <id>NamespaceInfoImpl--2524850:17f4b5b279a:-7ffe</id>
  </namespace>
  <title>ne_10m_populated_places</title>
  <keywords>
    <string>features</string>
    <string>ne_10m_populated_places</string>
  </keywords>
  <nativeCRS>GEOGCS[&quot;WGS 84&quot;, 
  DATUM[&quot;World Geodetic System 1984&quot;, 
    SPHEROID[&quot;WGS 84&quot;, 6378137.0, 298.257223563, AUTHORITY[&quot;EPSG&quot;,&quot;7030&quot;]], 
    AUTHORITY[&quot;EPSG&quot;,&quot;6326&quot;]], 
  PRIMEM[&quot;Greenwich&quot;, 0.0, AUTHORITY[&quot;EPSG&quot;,&quot;8901&quot;]], 
  UNIT[&quot;degree&quot;, 0.017453292519943295], 
  AXIS[&quot;Geodetic longitude&quot;, EAST], 
  AXIS[&quot;Geodetic latitude&quot;, NORTH], 
  AUTHORITY[&quot;EPSG&quot;,&quot;4326&quot;]]</nativeCRS>
  <srs>EPSG:4326</srs>
  <nativeBoundingBox>
    <minx>-179.5899789</minx>
    <maxx>179.3833036</maxx>
    <miny>-89.9999998</miny>
    <maxy>82.4833232</maxy>
    <crs>EPSG:4326</crs>
  </nativeBoundingBox>
  <latLonBoundingBox>
    <minx>-179.5899789</minx>
    <maxx>179.3833036</maxx>
    <miny>-89.9999998</miny>
    <maxy>82.4833232</maxy>
    <crs>EPSG:4326</crs>
  </latLonBoundingBox>
  <projectionPolicy>NONE</projectionPolicy>
  <enabled>true</enabled>
  <metadata>
    <entry key="recalculate-bounds">true</entry>
  </metadata>
  <store class="dataStore">
    <id>DataStoreInfoImpl-278efbc3:17f5052b3fc:-7fec</id>
  </store>
  <serviceConfiguration>false</serviceConfiguration>
  <simpleConversionEnabled>false</simpleConversionEnabled>
  <maxFeatures>0</maxFeatures>
  <numDecimals>0</numDecimals>
  <padWithZeros>false</padWithZeros>
  <forcedDecimal>false</forcedDecimal>
  <attributes>
    <attribute>
      <name>the_geom</name>
      <minOccurs>0</minOccurs>
      <maxOccurs>0</maxOccurs>
      <nillable>false</nillable>
      <binding>org.locationtech.jts.geom.Point</binding>
    </attribute>
    <attribute>
      <name>SCALERANK</name>
      <minOccurs>0</minOccurs>
      <maxOccurs>0</maxOccurs>
      <nillable>false</nillable>
      <binding>java.lang.Integer</binding>
    </attribute>
    <attribute>
      <name>NATSCALE</name>
      <minOccurs>0</minOccurs>
      <maxOccurs>0</maxOccurs>
      <nillable>false</nillable>
      <binding>java.lang.Integer</binding>
    </attribute>
    <attribute>
      <name>LABELRANK</name>
      <minOccurs>0</minOccurs>
      <maxOccurs>0</maxOccurs>
      <nillable>false</nillable>
      <binding>java.lang.Integer</binding>
    </attribute>
    <attribute>
      <name>FEATURECLA</name>
      <minOccurs>0</minOccurs>
      <maxOccurs>0</maxOccurs>
      <nillable>false</nillable>
      <binding>java.lang.String</binding>
    </attribute>
    <attribute>
      <name>NAME</name>
      <minOccurs>0</minOccurs>
      <maxOccurs>0</maxOccurs>
      <nillable>false</nillable>
      <binding>java.lang.String</binding>
    </attribute>
    <attribute>
      <name>NAMEPAR</name>
      <minOccurs>0</minOccurs>
      <maxOccurs>0</maxOccurs>
      <nillable>false</nillable>
      <binding>java.lang.String</binding>
    </attribute>
    <attribute>
      <name>NAMEALT</name>
      <minOccurs>0</minOccurs>
      <maxOccurs>0</maxOccurs>
      <nillable>false</nillable>
      <binding>java.lang.String</binding>
    </attribute>
    <attribute>
      <name>NAMEASCII</name>
      <minOccurs>0</minOccurs>
      <maxOccurs>0</maxOccurs>
      <nillable>false</nillable>
      <binding>java.lang.String</binding>
    </attribute>
    <attribute>
      <name>ADM0CAP</name>
      <minOccurs>0</minOccurs>
      <maxOccurs>0</maxOccurs>
      <nillable>false</nillable>
      <binding>java.lang.Integer</binding>
    </attribute>
    <attribute>
      <name>CAPIN</name>
      <minOccurs>0</minOccurs>
      <maxOccurs>0</maxOccurs>
      <nillable>false</nillable>
      <binding>java.lang.String</binding>
    </attribute>
    <attribute>
      <name>WORLDCITY</name>
      <minOccurs>0</minOccurs>
      <maxOccurs>0</maxOccurs>
      <nillable>false</nillable>
      <binding>java.lang.Integer</binding>
    </attribute>
    <attribute>
      <name>MEGACITY</name>
      <minOccurs>0</minOccurs>
      <maxOccurs>0</maxOccurs>
      <nillable>false</nillable>
      <binding>java.lang.Integer</binding>
    </attribute>
    <attribute>
      <name>SOV0NAME</name>
      <minOccurs>0</minOccurs>
      <maxOccurs>0</maxOccurs>
      <nillable>false</nillable>
      <binding>java.lang.String</binding>
    </attribute>
    <attribute>
      <name>SOV_A3</name>
      <minOccurs>0</minOccurs>
      <maxOccurs>0</maxOccurs>
      <nillable>false</nillable>
      <binding>java.lang.String</binding>
    </attribute>
    <attribute>
      <name>ADM0NAME</name>
      <minOccurs>0</minOccurs>
      <maxOccurs>0</maxOccurs>
      <nillable>false</nillable>
      <binding>java.lang.String</binding>
    </attribute>
    <attribute>
      <name>ADM0_A3</name>
      <minOccurs>0</minOccurs>
      <maxOccurs>0</maxOccurs>
      <nillable>false</nillable>
      <binding>java.lang.String</binding>
    </attribute>
    <attribute>
      <name>ADM1NAME</name>
      <minOccurs>0</minOccurs>
      <maxOccurs>0</maxOccurs>
      <nillable>false</nillable>
      <binding>java.lang.String</binding>
    </attribute>
    <attribute>
      <name>ISO_A2</name>
      <minOccurs>0</minOccurs>
      <maxOccurs>0</maxOccurs>
      <nillable>false</nillable>
      <binding>java.lang.String</binding>
    </attribute>
    <attribute>
      <name>NOTE</name>
      <minOccurs>0</minOccurs>
      <maxOccurs>0</maxOccurs>
      <nillable>false</nillable>
      <binding>java.lang.String</binding>
    </attribute>
    <attribute>
      <name>LATITUDE</name>
      <minOccurs>0</minOccurs>
      <maxOccurs>0</maxOccurs>
      <nillable>false</nillable>
      <binding>java.lang.Double</binding>
    </attribute>
    <attribute>
      <name>LONGITUDE</name>
      <minOccurs>0</minOccurs>
      <maxOccurs>0</maxOccurs>
      <nillable>false</nillable>
      <binding>java.lang.Double</binding>
    </attribute>
    <attribute>
      <name>POP_MAX</name>
      <minOccurs>0</minOccurs>
      <maxOccurs>0</maxOccurs>
      <nillable>false</nillable>
      <binding>java.lang.Long</binding>
    </attribute>
    <attribute>
      <name>POP_MIN</name>
      <minOccurs>0</minOccurs>
      <maxOccurs>0</maxOccurs>
      <nillable>false</nillable>
      <binding>java.lang.Long</binding>
    </attribute>
    <attribute>
      <name>POP_OTHER</name>
      <minOccurs>0</minOccurs>
      <maxOccurs>0</maxOccurs>
      <nillable>false</nillable>
      <binding>java.lang.Long</binding>
    </attribute>
    <attribute>
      <name>RANK_MAX</name>
      <minOccurs>0</minOccurs>
      <maxOccurs>0</maxOccurs>
      <nillable>false</nillable>
      <binding>java.lang.Integer</binding>
    </attribute>
    <attribute>
      <name>RANK_MIN</name>
      <minOccurs>0</minOccurs>
      <maxOccurs>0</maxOccurs>
      <nillable>false</nillable>
      <binding>java.lang.Integer</binding>
    </attribute>
    <attribute>
      <name>MEGANAME</name>
      <minOccurs>0</minOccurs>
      <maxOccurs>0</maxOccurs>
      <nillable>false</nillable>
      <binding>java.lang.String</binding>
    </attribute>
    <attribute>
      <name>LS_NAME</name>
      <minOccurs>0</minOccurs>
      <maxOccurs>0</maxOccurs>
      <nillable>false</nillable>
      <binding>java.lang.String</binding>
    </attribute>
    <attribute>
      <name>MAX_POP10</name>
      <minOccurs>0</minOccurs>
      <maxOccurs>0</maxOccurs>
      <nillable>false</nillable>
      <binding>java.lang.Long</binding>
    </attribute>
    <attribute>
      <name>MAX_POP20</name>
      <minOccurs>0</minOccurs>
      <maxOccurs>0</maxOccurs>
      <nillable>false</nillable>
      <binding>java.lang.Long</binding>
    </attribute>
    <attribute>
      <name>MAX_POP50</name>
      <minOccurs>0</minOccurs>
      <maxOccurs>0</maxOccurs>
      <nillable>false</nillable>
      <binding>java.lang.Long</binding>
    </attribute>
    <attribute>
      <name>MAX_POP300</name>
      <minOccurs>0</minOccurs>
      <maxOccurs>0</maxOccurs>
      <nillable>false</nillable>
      <binding>java.lang.Long</binding>
    </attribute>
    <attribute>
      <name>MAX_POP310</name>
      <minOccurs>0</minOccurs>
      <maxOccurs>0</maxOccurs>
      <nillable>false</nillable>
      <binding>java.lang.Long</binding>
    </attribute>
    <attribute>
      <name>MAX_NATSCA</name>
      <minOccurs>0</minOccurs>
      <maxOccurs>0</maxOccurs>
      <nillable>false</nillable>
      <binding>java.lang.Long</binding>
    </attribute>
    <attribute>
      <name>MIN_AREAKM</name>
      <minOccurs>0</minOccurs>
      <maxOccurs>0</maxOccurs>
      <nillable>false</nillable>
      <binding>java.lang.Long</binding>
    </attribute>
    <attribute>
      <name>MAX_AREAKM</name>
      <minOccurs>0</minOccurs>
      <maxOccurs>0</maxOccurs>
      <nillable>false</nillable>
      <binding>java.lang.Long</binding>
    </attribute>
    <attribute>
      <name>MIN_AREAMI</name>
      <minOccurs>0</minOccurs>
      <maxOccurs>0</maxOccurs>
      <nillable>false</nillable>
      <binding>java.lang.Long</binding>
    </attribute>
    <attribute>
      <name>MAX_AREAMI</name>
      <minOccurs>0</minOccurs>
      <maxOccurs>0</maxOccurs>
      <nillable>false</nillable>
      <binding>java.lang.Long</binding>
    </attribute>
    <attribute>
      <name>MIN_PERKM</name>
      <minOccurs>0</minOccurs>
      <maxOccurs>0</maxOccurs>
      <nillable>false</nillable>
      <binding>java.lang.Long</binding>
    </attribute>
    <attribute>
      <name>MAX_PERKM</name>
      <minOccurs>0</minOccurs>
      <maxOccurs>0</maxOccurs>
      <nillable>false</nillable>
      <binding>java.lang.Long</binding>
    </attribute>
    <attribute>
      <name>MIN_PERMI</name>
      <minOccurs>0</minOccurs>
      <maxOccurs>0</maxOccurs>
      <nillable>false</nillable>
      <binding>java.lang.Long</binding>
    </attribute>
    <attribute>
      <name>MAX_PERMI</name>
      <minOccurs>0</minOccurs>
      <maxOccurs>0</maxOccurs>
      <nillable>false</nillable>
      <binding>java.lang.Long</binding>
    </attribute>
    <attribute>
      <name>MIN_BBXMIN</name>
      <minOccurs>0</minOccurs>
      <maxOccurs>0</maxOccurs>
      <nillable>false</nillable>
      <binding>java.lang.Double</binding>
    </attribute>
    <attribute>
      <name>MAX_BBXMIN</name>
      <minOccurs>0</minOccurs>
      <maxOccurs>0</maxOccurs>
      <nillable>false</nillable>
      <binding>java.lang.Double</binding>
    </attribute>
    <attribute>
      <name>MIN_BBXMAX</name>
      <minOccurs>0</minOccurs>
      <maxOccurs>0</maxOccurs>
      <nillable>false</nillable>
      <binding>java.lang.Double</binding>
    </attribute>
    <attribute>
      <name>MAX_BBXMAX</name>
      <minOccurs>0</minOccurs>
      <maxOccurs>0</maxOccurs>
      <nillable>false</nillable>
      <binding>java.lang.Double</binding>
    </attribute>
    <attribute>
      <name>MIN_BBYMIN</name>
      <minOccurs>0</minOccurs>
      <maxOccurs>0</maxOccurs>
      <nillable>false</nillable>
      <binding>java.lang.Double</binding>
    </attribute>
    <attribute>
      <name>MAX_BBYMIN</name>
      <minOccurs>0</minOccurs>
      <maxOccurs>0</maxOccurs>
      <nillable>false</nillable>
      <binding>java.lang.Double</binding>
    </attribute>
    <attribute>
      <name>MIN_BBYMAX</name>
      <minOccurs>0</minOccurs>
      <maxOccurs>0</maxOccurs>
      <nillable>false</nillable>
      <binding>java.lang.Double</binding>
    </attribute>
    <attribute>
      <name>MAX_BBYMAX</name>
      <minOccurs>0</minOccurs>
      <maxOccurs>0</maxOccurs>
      <nillable>false</nillable>
      <binding>java.lang.Double</binding>
    </attribute>
    <attribute>
      <name>MEAN_BBXC</name>
      <minOccurs>0</minOccurs>
      <maxOccurs>0</maxOccurs>
      <nillable>false</nillable>
      <binding>java.lang.Double</binding>
    </attribute>
    <attribute>
      <name>MEAN_BBYC</name>
      <minOccurs>0</minOccurs>
      <maxOccurs>0</maxOccurs>
      <nillable>false</nillable>
      <binding>java.lang.Double</binding>
    </attribute>
    <attribute>
      <name>TIMEZONE</name>
      <minOccurs>0</minOccurs>
      <maxOccurs>0</maxOccurs>
      <nillable>false</nillable>
      <binding>java.lang.String</binding>
    </attribute>
    <attribute>
      <name>UN_FID</name>
      <minOccurs>0</minOccurs>
      <maxOccurs>0</maxOccurs>
      <nillable>false</nillable>
      <binding>java.lang.Integer</binding>
    </attribute>
    <attribute>
      <name>POP1950</name>
      <minOccurs>0</minOccurs>
      <maxOccurs>0</maxOccurs>
      <nillable>false</nillable>
      <binding>java.lang.Long</binding>
    </attribute>
    <attribute>
      <name>POP1955</name>
      <minOccurs>0</minOccurs>
      <maxOccurs>0</maxOccurs>
      <nillable>false</nillable>
      <binding>java.lang.Long</binding>
    </attribute>
    <attribute>
      <name>POP1960</name>
      <minOccurs>0</minOccurs>
      <maxOccurs>0</maxOccurs>
      <nillable>false</nillable>
      <binding>java.lang.Long</binding>
    </attribute>
    <attribute>
      <name>POP1965</name>
      <minOccurs>0</minOccurs>
      <maxOccurs>0</maxOccurs>
      <nillable>false</nillable>
      <binding>java.lang.Long</binding>
    </attribute>
    <attribute>
      <name>POP1970</name>
      <minOccurs>0</minOccurs>
      <maxOccurs>0</maxOccurs>
      <nillable>false</nillable>
      <binding>java.lang.Long</binding>
    </attribute>
    <attribute>
      <name>POP1975</name>
      <minOccurs>0</minOccurs>
      <maxOccurs>0</maxOccurs>
      <nillable>false</nillable>
      <binding>java.lang.Long</binding>
    </attribute>
    <attribute>
      <name>POP1980</name>
      <minOccurs>0</minOccurs>
      <maxOccurs>0</maxOccurs>
      <nillable>false</nillable>
      <binding>java.lang.Long</binding>
    </attribute>
    <attribute>
      <name>POP1985</name>
      <minOccurs>0</minOccurs>
      <maxOccurs>0</maxOccurs>
      <nillable>false</nillable>
      <binding>java.lang.Long</binding>
    </attribute>
    <attribute>
      <name>POP1990</name>
      <minOccurs>0</minOccurs>
      <maxOccurs>0</maxOccurs>
      <nillable>false</nillable>
      <binding>java.lang.Long</binding>
    </attribute>
    <attribute>
      <name>POP1995</name>
      <minOccurs>0</minOccurs>
      <maxOccurs>0</maxOccurs>
      <nillable>false</nillable>
      <binding>java.lang.Long</binding>
    </attribute>
    <attribute>
      <name>POP2000</name>
      <minOccurs>0</minOccurs>
      <maxOccurs>0</maxOccurs>
      <nillable>false</nillable>
      <binding>java.lang.Long</binding>
    </attribute>
    <attribute>
      <name>POP2005</name>
      <minOccurs>0</minOccurs>
      <maxOccurs>0</maxOccurs>
      <nillable>false</nillable>
      <binding>java.lang.Long</binding>
    </attribute>
    <attribute>
      <name>POP2010</name>
      <minOccurs>0</minOccurs>
      <maxOccurs>0</maxOccurs>
      <nillable>false</nillable>
      <binding>java.lang.Long</binding>
    </attribute>
    <attribute>
      <name>POP2015</name>
      <minOccurs>0</minOccurs>
      <maxOccurs>0</maxOccurs>
      <nillable>false</nillable>
      <binding>java.lang.Long</binding>
    </attribute>
    <attribute>
      <name>POP2020</name>
      <minOccurs>0</minOccurs>
      <maxOccurs>0</maxOccurs>
      <nillable>false</nillable>
      <binding>java.lang.Long</binding>
    </attribute>
    <attribute>
      <name>POP2025</name>
      <minOccurs>0</minOccurs>
      <maxOccurs>0</maxOccurs>
      <nillable>false</nillable>
      <binding>java.lang.Long</binding>
    </attribute>
    <attribute>
      <name>POP2050</name>
      <minOccurs>0</minOccurs>
      <maxOccurs>0</maxOccurs>
      <nillable>false</nillable>
      <binding>java.lang.Long</binding>
    </attribute>
    <attribute>
      <name>MIN_ZOOM</name>
      <minOccurs>0</minOccurs>
      <maxOccurs>0</maxOccurs>
      <nillable>false</nillable>
      <binding>java.lang.Double</binding>
    </attribute>
    <attribute>
      <name>WIKIDATAID</name>
      <minOccurs>0</minOccurs>
      <maxOccurs>0</maxOccurs>
      <nillable>false</nillable>
      <binding>java.lang.String</binding>
    </attribute>
    <attribute>
      <name>WOF_ID</name>
      <minOccurs>0</minOccurs>
      <maxOccurs>0</maxOccurs>
      <nillable>false</nillable>
      <binding>java.lang.Long</binding>
    </attribute>
    <attribute>
      <name>CAPALT</name>
      <minOccurs>0</minOccurs>
      <maxOccurs>0</maxOccurs>
      <nillable>false</nillable>
      <binding>java.lang.Integer</binding>
    </attribute>
    <attribute>
      <name>NAME_EN</name>
      <minOccurs>0</minOccurs>
      <maxOccurs>0</maxOccurs>
      <nillable>false</nillable>
      <binding>java.lang.String</binding>
    </attribute>
    <attribute>
      <name>NAME_DE</name>
      <minOccurs>0</minOccurs>
      <maxOccurs>0</maxOccurs>
      <nillable>false</nillable>
      <binding>java.lang.String</binding>
    </attribute>
    <attribute>
      <name>NAME_ES</name>
      <minOccurs>0</minOccurs>
      <maxOccurs>0</maxOccurs>
      <nillable>false</nillable>
      <binding>java.lang.String</binding>
    </attribute>
    <attribute>
      <name>NAME_FR</name>
      <minOccurs>0</minOccurs>
      <maxOccurs>0</maxOccurs>
      <nillable>false</nillable>
      <binding>java.lang.String</binding>
    </attribute>
    <attribute>
      <name>NAME_PT</name>
      <minOccurs>0</minOccurs>
      <maxOccurs>0</maxOccurs>
      <nillable>false</nillable>
      <binding>java.lang.String</binding>
    </attribute>
    <attribute>
      <name>NAME_RU</name>
      <minOccurs>0</minOccurs>
      <maxOccurs>0</maxOccurs>
      <nillable>false</nillable>
      <binding>java.lang.String</binding>
    </attribute>
    <attribute>
      <name>NAME_ZH</name>
      <minOccurs>0</minOccurs>
      <maxOccurs>0</maxOccurs>
      <nillable>false</nillable>
      <binding>java.lang.String</binding>
    </attribute>
    <attribute>
      <name>LABEL</name>
      <minOccurs>0</minOccurs>
      <maxOccurs>0</maxOccurs>
      <nillable>false</nillable>
      <binding>java.lang.String</binding>
    </attribute>
    <attribute>
      <name>NAME_AR</name>
      <minOccurs>0</minOccurs>
      <maxOccurs>0</maxOccurs>
      <nillable>false</nillable>
      <binding>java.lang.String</binding>
    </attribute>
    <attribute>
      <name>NAME_BN</name>
      <minOccurs>0</minOccurs>
      <maxOccurs>0</maxOccurs>
      <nillable>false</nillable>
      <binding>java.lang.String</binding>
    </attribute>
    <attribute>
      <name>NAME_EL</name>
      <minOccurs>0</minOccurs>
      <maxOccurs>0</maxOccurs>
      <nillable>false</nillable>
      <binding>java.lang.String</binding>
    </attribute>
    <attribute>
      <name>NAME_HI</name>
      <minOccurs>0</minOccurs>
      <maxOccurs>0</maxOccurs>
      <nillable>false</nillable>
      <binding>java.lang.String</binding>
    </attribute>
    <attribute>
      <name>NAME_HU</name>
      <minOccurs>0</minOccurs>
      <maxOccurs>0</maxOccurs>
      <nillable>false</nillable>
      <binding>java.lang.String</binding>
    </attribute>
    <attribute>
      <name>NAME_ID</name>
      <minOccurs>0</minOccurs>
      <maxOccurs>0</maxOccurs>
      <nillable>false</nillable>
      <binding>java.lang.String</binding>
    </attribute>
    <attribute>
      <name>NAME_IT</name>
      <minOccurs>0</minOccurs>
      <maxOccurs>0</maxOccurs>
      <nillable>false</nillable>
      <binding>java.lang.String</binding>
    </attribute>
    <attribute>
      <name>NAME_JA</name>
      <minOccurs>0</minOccurs>
      <maxOccurs>0</maxOccurs>
      <nillable>false</nillable>
      <binding>java.lang.String</binding>
    </attribute>
    <attribute>
      <name>NAME_KO</name>
      <minOccurs>0</minOccurs>
      <maxOccurs>0</maxOccurs>
      <nillable>false</nillable>
      <binding>java.lang.String</binding>
    </attribute>
    <attribute>
      <name>NAME_NL</name>
      <minOccurs>0</minOccurs>
      <maxOccurs>0</maxOccurs>
      <nillable>false</nillable>
      <binding>java.lang.String</binding>
    </attribute>
    <attribute>
      <name>NAME_PL</name>
      <minOccurs>0</minOccurs>
      <maxOccurs>0</maxOccurs>
      <nillable>false</nillable>
      <binding>java.lang.String</binding>
    </attribute>
    <attribute>
      <name>NAME_SV</name>
      <minOccurs>0</minOccurs>
      <maxOccurs>0</maxOccurs>
      <nillable>false</nillable>
      <binding>java.lang.String</binding>
    </attribute>
    <attribute>
      <name>NAME_TR</name>
      <minOccurs>0</minOccurs>
      <maxOccurs>0</maxOccurs>
      <nillable>false</nillable>
      <binding>java.lang.String</binding>
    </attribute>
    <attribute>
      <name>NAME_VI</name>
      <minOccurs>0</minOccurs>
      <maxOccurs>0</maxOccurs>
      <nillable>false</nillable>
      <binding>java.lang.String</binding>
    </attribute>
    <attribute>
      <name>NE_ID</name>
      <minOccurs>0</minOccurs>
      <maxOccurs>0</maxOccurs>
      <nillable>false</nillable>
      <binding>java.lang.Long</binding>
    </attribute>
    <attribute>
      <name>NAME_FA</name>
      <minOccurs>0</minOccurs>
      <maxOccurs>0</maxOccurs>
      <nillable>false</nillable>
      <binding>java.lang.String</binding>
    </attribute>
    <attribute>
      <name>NAME_HE</name>
      <minOccurs>0</minOccurs>
      <maxOccurs>0</maxOccurs>
      <nillable>false</nillable>
      <binding>java.lang.String</binding>
    </attribute>
    <attribute>
      <name>NAME_UK</name>
      <minOccurs>0</minOccurs>
      <maxOccurs>0</maxOccurs>
      <nillable>false</nillable>
      <binding>java.lang.String</binding>
    </attribute>
    <attribute>
      <name>NAME_UR</name>
      <minOccurs>0</minOccurs>
      <maxOccurs>0</maxOccurs>
      <nillable>false</nillable>
      <binding>java.lang.String</binding>
    </attribute>
    <attribute>
      <name>NAME_ZHT</name>
      <minOccurs>0</minOccurs>
      <maxOccurs>0</maxOccurs>
      <nillable>false</nillable>
      <binding>java.lang.String</binding>
    </attribute>
    <attribute>
      <name>GEONAMESID</name>
      <minOccurs>0</minOccurs>
      <maxOccurs>0</maxOccurs>
      <nillable>false</nillable>
      <binding>java.lang.Long</binding>
    </attribute>
    <attribute>
      <name>FCLASS_ISO</name>
      <minOccurs>0</minOccurs>
      <maxOccurs>0</maxOccurs>
      <nillable>false</nillable>
      <binding>java.lang.String</binding>
    </attribute>
    <attribute>
      <name>FCLASS_US</name>
      <minOccurs>0</minOccurs>
      <maxOccurs>0</maxOccurs>
      <nillable>false</nillable>
      <binding>java.lang.String</binding>
    </attribute>
    <attribute>
      <name>FCLASS_FR</name>
      <minOccurs>0</minOccurs>
      <maxOccurs>0</maxOccurs>
      <nillable>false</nillable>
      <binding>java.lang.String</binding>
    </attribute>
    <attribute>
      <name>FCLASS_RU</name>
      <minOccurs>0</minOccurs>
      <maxOccurs>0</maxOccurs>
      <nillable>false</nillable>
      <binding>java.lang.String</binding>
    </attribute>
    <attribute>
      <name>FCLASS_ES</name>
      <minOccurs>0</minOccurs>
      <maxOccurs>0</maxOccurs>
      <nillable>false</nillable>
      <binding>java.lang.String</binding>
    </attribute>
    <attribute>
      <name>FCLASS_CN</name>
      <minOccurs>0</minOccurs>
      <maxOccurs>0</maxOccurs>
      <nillable>false</nillable>
      <binding>java.lang.String</binding>
    </attribute>
    <attribute>
      <name>FCLASS_TW</name>
      <minOccurs>0</minOccurs>
      <maxOccurs>0</maxOccurs>
      <nillable>false</nillable>
      <binding>java.lang.String</binding>
    </attribute>
    <attribute>
      <name>FCLASS_IN</name>
      <minOccurs>0</minOccurs>
      <maxOccurs>0</maxOccurs>
      <nillable>false</nillable>
      <binding>java.lang.String</binding>
    </attribute>
    <attribute>
      <name>FCLASS_NP</name>
      <minOccurs>0</minOccurs>
      <maxOccurs>0</maxOccurs>
      <nillable>false</nillable>
      <binding>java.lang.String</binding>
    </attribute>
    <attribute>
      <name>FCLASS_PK</name>
      <minOccurs>0</minOccurs>
      <maxOccurs>0</maxOccurs>
      <nillable>false</nillable>
      <binding>java.lang.String</binding>
    </attribute>
    <attribute>
      <name>FCLASS_DE</name>
      <minOccurs>0</minOccurs>
      <maxOccurs>0</maxOccurs>
      <nillable>false</nillable>
      <binding>java.lang.String</binding>
    </attribute>
    <attribute>
      <name>FCLASS_GB</name>
      <minOccurs>0</minOccurs>
      <maxOccurs>0</maxOccurs>
      <nillable>false</nillable>
      <binding>java.lang.String</binding>
    </attribute>
    <attribute>
      <name>FCLASS_BR</name>
      <minOccurs>0</minOccurs>
      <maxOccurs>0</maxOccurs>
      <nillable>false</nillable>
      <binding>java.lang.String</binding>
    </attribute>
    <attribute>
      <name>FCLASS_IL</name>
      <minOccurs>0</minOccurs>
      <maxOccurs>0</maxOccurs>
      <nillable>false</nillable>
      <binding>java.lang.String</binding>
    </attribute>
    <attribute>
      <name>FCLASS_PS</name>
      <minOccurs>0</minOccurs>
      <maxOccurs>0</maxOccurs>
      <nillable>false</nillable>
      <binding>java.lang.String</binding>
    </attribute>
    <attribute>
      <name>FCLASS_SA</name>
      <minOccurs>0</minOccurs>
      <maxOccurs>0</maxOccurs>
      <nillable>false</nillable>
      <binding>java.lang.String</binding>
    </attribute>
    <attribute>
      <name>FCLASS_EG</name>
      <minOccurs>0</minOccurs>
      <maxOccurs>0</maxOccurs>
      <nillable>false</nillable>
      <binding>java.lang.String</binding>
    </attribute>
    <attribute>
      <name>FCLASS_MA</name>
      <minOccurs>0</minOccurs>
      <maxOccurs>0</maxOccurs>
      <nillable>false</nillable>
      <binding>java.lang.String</binding>
    </attribute>
    <attribute>
      <name>FCLASS_PT</name>
      <minOccurs>0</minOccurs>
      <maxOccurs>0</maxOccurs>
      <nillable>false</nillable>
      <binding>java.lang.String</binding>
    </attribute>
    <attribute>
      <name>FCLASS_AR</name>
      <minOccurs>0</minOccurs>
      <maxOccurs>0</maxOccurs>
      <nillable>false</nillable>
      <binding>java.lang.String</binding>
    </attribute>
    <attribute>
      <name>FCLASS_JP</name>
      <minOccurs>0</minOccurs>
      <maxOccurs>0</maxOccurs>
      <nillable>false</nillable>
      <binding>java.lang.String</binding>
    </attribute>
    <attribute>
      <name>FCLASS_KO</name>
      <minOccurs>0</minOccurs>
      <maxOccurs>0</maxOccurs>
      <nillable>false</nillable>
      <binding>java.lang.String</binding>
    </attribute>
    <attribute>
      <name>FCLASS_VN</name>
      <minOccurs>0</minOccurs>
      <maxOccurs>0</maxOccurs>
      <nillable>false</nillable>
      <binding>java.lang.String</binding>
    </attribute>
    <attribute>
      <name>FCLASS_TR</name>
      <minOccurs>0</minOccurs>
      <maxOccurs>0</maxOccurs>
      <nillable>false</nillable>
      <binding>java.lang.String</binding>
    </attribute>
    <attribute>
      <name>FCLASS_ID</name>
      <minOccurs>0</minOccurs>
      <maxOccurs>0</maxOccurs>
      <nillable>false</nillable>
      <binding>java.lang.String</binding>
    </attribute>
    <attribute>
      <name>FCLASS_PL</name>
      <minOccurs>0</minOccurs>
      <maxOccurs>0</maxOccurs>
      <nillable>false</nillable>
      <binding>java.lang.String</binding>
    </attribute>
    <attribute>
      <name>FCLASS_GR</name>
      <minOccurs>0</minOccurs>
      <maxOccurs>0</maxOccurs>
      <nillable>false</nillable>
      <binding>java.lang.String</binding>
    </attribute>
    <attribute>
      <name>FCLASS_IT</name>
      <minOccurs>0</minOccurs>
      <maxOccurs>0</maxOccurs>
      <nillable>false</nillable>
      <binding>java.lang.String</binding>
    </attribute>
    <attribute>
      <name>FCLASS_NL</name>
      <minOccurs>0</minOccurs>
      <maxOccurs>0</maxOccurs>
      <nillable>false</nillable>
      <binding>java.lang.String</binding>
    </attribute>
    <attribute>
      <name>FCLASS_SE</name>
      <minOccurs>0</minOccurs>
      <maxOccurs>0</maxOccurs>
      <nillable>false</nillable>
      <binding>java.lang.String</binding>
    </attribute>
    <attribute>
      <name>FCLASS_BD</name>
      <minOccurs>0</minOccurs>
      <maxOccurs>0</maxOccurs>
      <nillable>false</nillable>
      <binding>java.lang.String</binding>
    </attribute>
    <attribute>
      <name>FCLASS_UA</name>
      <minOccurs>0</minOccurs>
      <maxOccurs>0</maxOccurs>
      <nillable>false</nillable>
      <binding>java.lang.String</binding>
    </attribute>
  </attributes>
  <overridingServiceSRS>false</overridingServiceSRS>
  <skipNumberMatched>false</skipNumberMatched>
  <circularArcPresent>false</circularArcPresent>
</featureType>