<layer>
  <name>ne_110m_admin_1_states_provinces</name>
  <id>LayerInfoImpl--2524850:17f4b5b279a:-7ff7</id>
  <type>VECTOR</type>
  <defaultStyle>
    <id>StyleInfoImpl--2524850:17f4b5b279a:-7fe2</id>
  </defaultStyle>
  <resource class="featureType">
    <id>FeatureTypeInfoImpl--2524850:17f4b5b279a:-7ff8</id>
  </resource>
  <attribution>
    <logoWidth>0</logoWidth>
    <logoHeight>0</logoHeight>
  </attribution>
  <dateCreated>2022-03-02 16:05:22.161 UTC</dateCreated>
  <dateModified>2022-03-02 18:37:22.233 UTC</dateModified>
</layer>